<ElfText>
 <Entry>
  <MemoryOffsets>
   <MemoryOffset Module="Main">4</MemoryOffset>
  </MemoryOffsets>
  <LiteralPointers/>
  <MipsPointers/>
  <JapaneseText>レイヴアビリティLV1</JapaneseText>
  <EnglishText/>
  <Notes/>
  <EditFlag>0</EditFlag>
 </Entry>
 <Entry>
  <MemoryOffsets>
   <MemoryOffset Module="Main">48</MemoryOffset>
  </MemoryOffsets>
  <LiteralPointers/>
  <MipsPointers/>
  <JapaneseText>&lt;Color:340>レイヴアビリティ&lt;Color:440>にはそれぞれ</JapaneseText>
  <EnglishText/>
  <Notes/>
  <EditFlag>0</EditFlag>
 </Entry>
 <Entry>
  <MemoryOffsets>
   <MemoryOffset Module="Main">179</MemoryOffset>
  </MemoryOffsets>
  <LiteralPointers/>
  <MipsPointers/>
  <JapaneseText>レベルが存在しています。</JapaneseText>
  <EnglishText/>
  <Notes/>
  <EditFlag>0</EditFlag>
 </Entry>
 <Entry>
  <MemoryOffsets>
   <MemoryOffset Module="Main">310</MemoryOffset>
  </MemoryOffsets>
  <LiteralPointers/>
  <MipsPointers/>
  <JapaneseText>同じ&lt;Color:340>レイヴアビリティ&lt;Color:440>でも</JapaneseText>
  <EnglishText/>
  <Notes/>
  <EditFlag>0</EditFlag>
 </Entry>
 <Entry>
  <MemoryOffsets>
   <MemoryOffset Module="Main">441</MemoryOffset>
  </MemoryOffsets>
  <LiteralPointers/>
  <MipsPointers/>
  <JapaneseText>よりレベルの高いものが</JapaneseText>
  <EnglishText/>
  <Notes/>
  <EditFlag>0</EditFlag>
 </Entry>
 <Entry>
  <MemoryOffsets>
   <MemoryOffset Module="Main">572</MemoryOffset>
  </MemoryOffsets>
  <LiteralPointers/>
  <MipsPointers/>
  <JapaneseText>良い効果を発揮します。</JapaneseText>
  <EnglishText/>
  <Notes/>
  <EditFlag>0</EditFlag>
 </Entry>
 <Entry>
  <MemoryOffsets>
   <MemoryOffset Module="Main">703</MemoryOffset>
  </MemoryOffsets>
  <LiteralPointers/>
  <MipsPointers/>
  <JapaneseText>　</JapaneseText>
  <EnglishText/>
  <Notes/>
  <EditFlag>0</EditFlag>
 </Entry>
 <Entry>
  <MemoryOffsets>
   <MemoryOffset Module="Main">834</MemoryOffset>
  </MemoryOffsets>
  <LiteralPointers/>
  <MipsPointers/>
  <JapaneseText>また、同じ種類のアビリティを</JapaneseText>
  <EnglishText/>
  <Notes/>
  <EditFlag>0</EditFlag>
 </Entry>
 <Entry>
  <MemoryOffsets>
   <MemoryOffset Module="Main">965</MemoryOffset>
  </MemoryOffsets>
  <LiteralPointers/>
  <MipsPointers/>
  <JapaneseText>レベルが違うからといって</JapaneseText>
  <EnglishText/>
  <Notes/>
  <EditFlag>0</EditFlag>
 </Entry>
 <Entry>
  <MemoryOffsets>
   <MemoryOffset Module="Main">1096</MemoryOffset>
  </MemoryOffsets>
  <LiteralPointers/>
  <MipsPointers/>
  <JapaneseText>複数セットすることはできません。</JapaneseText>
  <EnglishText/>
  <Notes/>
  <EditFlag>0</EditFlag>
 </Entry>
</ElfText>
