<ElfText>
 <Entry>
  <MemoryOffsets>
   <MemoryOffset Module="Main">0x00000004</MemoryOffset>
  </MemoryOffsets>
  <LiteralPointers/>
  <MipsPointers/>
  <JapaneseText>イリアとの出会い１</JapaneseText>
  <EnglishText>A Meeting with Illia 1</EnglishText>
  <Notes/>
  <EditFlag>0</EditFlag>
 </Entry>
 <Entry>
  <MemoryOffsets>
   <MemoryOffset Module="Main">0x0000002E</MemoryOffset>
  </MemoryOffsets>
  <LiteralPointers/>
  <MipsPointers/>
  <JapaneseText>レグヌムに戻ったルカは</JapaneseText>
  <EnglishText>As Ruca returned to Regnum, he saw a boy</EnglishText>
  <Notes/>
  <EditFlag>0</EditFlag>
 </Entry>
 <Entry>
  <MemoryOffsets>
   <MemoryOffset Module="Main">0x0000008F</MemoryOffset>
  </MemoryOffsets>
  <LiteralPointers/>
  <MipsPointers/>
  <JapaneseText>&lt;Color:340>異能者捕縛適応法&lt;Color:440>で</JapaneseText>
  <EnglishText>being taken away under the &lt;Color:340>Deviant&lt;Color:440></EnglishText>
  <Notes/>
  <EditFlag>0</EditFlag>
 </Entry>
 <Entry>
  <MemoryOffsets>
   <MemoryOffset Module="Main">0x000000F0</MemoryOffset>
  </MemoryOffsets>
  <LiteralPointers/>
  <MipsPointers/>
  <JapaneseText>軍に連行される少年を見かけた。</JapaneseText>
  <EnglishText>&lt;Color:340>Reformation Act&lt;Color:440>.</EnglishText>
  <Notes/>
  <EditFlag>0</EditFlag>
 </Entry>
 <Entry>
  <MemoryOffsets>
   <MemoryOffset Module="Main">0x00000151</MemoryOffset>
  </MemoryOffsets>
  <LiteralPointers/>
  <MipsPointers/>
  <JapaneseText>露店の側で、ルカは教団兵に</JapaneseText>
  <EnglishText>He also met &lt;Color:340>Illia&lt;Color:440> being chased by the Church</EnglishText>
  <Notes/>
  <EditFlag>0</EditFlag>
 </Entry>
 <Entry>
  <MemoryOffsets>
   <MemoryOffset Module="Main">0x000001B2</MemoryOffset>
  </MemoryOffsets>
  <LiteralPointers/>
  <MipsPointers/>
  <JapaneseText>追われる少女&lt;Color:340>イリア&lt;Color:440>と出会う。</JapaneseText>
  <EnglishText>the hotdog stall.</EnglishText>
  <Notes/>
  <EditFlag>0</EditFlag>
 </Entry>
 <Entry>
  <MemoryOffsets>
   <MemoryOffset Module="Main">0x00000213</MemoryOffset>
  </MemoryOffsets>
  <LiteralPointers/>
  <MipsPointers/>
  <JapaneseText>教団兵からイリアを守ろうとした</JapaneseText>
  <EnglishText>When Ruca was protecting Illia from the</EnglishText>
  <Notes/>
  <EditFlag>0</EditFlag>
 </Entry>
 <Entry>
  <MemoryOffsets>
   <MemoryOffset Module="Main">0x00000274</MemoryOffset>
  </MemoryOffsets>
  <LiteralPointers/>
  <MipsPointers/>
  <JapaneseText>そのとき、ルカの眠っていた力</JapaneseText>
  <EnglishText>Church members, a slumbering power woke</EnglishText>
  <Notes/>
  <EditFlag>0</EditFlag>
 </Entry>
 <Entry>
  <MemoryOffsets>
   <MemoryOffset Module="Main">0x000002D5</MemoryOffset>
  </MemoryOffsets>
  <LiteralPointers/>
  <MipsPointers/>
  <JapaneseText>&lt;Color:340>転生者の力&lt;Color:440>が、目を覚ます</JapaneseText>
  <EnglishText>up from within him, the &lt;Color:340>power&lt;Color:440> of</EnglishText>
  <Notes/>
  <EditFlag>0</EditFlag>
 </Entry>
 <Entry>
  <MemoryOffsets>
   <MemoryOffset Module="Main">0x00000336</MemoryOffset>
  </MemoryOffsets>
  <LiteralPointers/>
  <MipsPointers/>
  <JapaneseText>new line</JapaneseText>
  <EnglishText>&lt;Color:340>a Reincarnator&lt;Color:440>.</EnglishText>
  <Notes/>
  <EditFlag>0</EditFlag>
 </Entry>
</ElfText>
